Metadata-Version: 2.1
Name: kohokoho
Version: 0.0.1
Summary: A CLI tool to obfuscate/anonymize a dataset.
Home-page: https://github.com/ayushsubedi/kohokoho
Author: Ayush Subedi
Author-email: ayush.subedi@gmail.com
License: UNKNOWN
Project-URL: Bug Reports, https://github.com/ayushsubedi/kohokoho/issues
Project-URL: Source, https://github.com/ayushsubedi/kohokoho
Platform: UNKNOWN
Requires-Python: >=3.6, <3.9
